splatwizard/__init__.py
splatwizard/_version.py
splatwizard-0.0.2.dist-info/licenses/LICENSE
splatwizard-0.0.2.dist-info/METADATA
splatwizard-0.0.2.dist-info/WHEEL
splatwizard-0.0.2.dist-info/top_level.txt
splatwizard-0.0.2.dist-info/RECORD
