Metadata-Version: 2.4
Name: splatwizard
Version: 0.0.2
Summary: splatwizard toolkit for research
Author-email: actcwlf <actcwlf@163.com>
License: MIT License
Keywords: Gaussian Splatting
Classifier: Programming Language :: Python :: 3
Requires-Python: >=3.7
License-File: LICENSE
Dynamic: license-file
